tah_example_pkg/__init__.py
tah_example_pkg/evaluate.py
tah_example_pkg/helpers.py
tah_example_pkg/model_class.py
tah_example_pkg/onnx_base.py
tah_example_pkg/predict.py
tah_example_pkg-1.0.0.dist-info/METADATA
tah_example_pkg-1.0.0.dist-info/WHEEL
tah_example_pkg-1.0.0.dist-info/RECORD
